delete
getch_
otp
show
update
write
