Metadata-Version: 1.0
Name: otp-cli
Version: 0.5.2
Summary: A CLI one-time password application that manages one-time passwords elegantly and with tons of customization.
Home-page: https://github.com/nathan-yan/otp_
Author: Nathan Yan
Author-email: nathancyan2002@gmail.com
License: UNKNOWN
Platform: UNKNOWN
